frarch/__init__.py
frarch/_version.txt
frarch/parser.py
frarch/datasets/__init__.py
frarch/datasets/caltech101.py
frarch/datasets/mit67.py
frarch/datasets/oxford_pets.py
frarch/datasets/transforms/__init__.py
frarch/datasets/transforms/pil_transforms.py
frarch/models/__init__.py
frarch/models/mock.py
frarch/models/classification/__init__.py
frarch/models/classification/cnn/__init__.py
frarch/models/classification/cnn/fashionCNN.py
frarch/models/classification/cnn/mitCNNs.py
frarch/models/classification/cnn/mnistCNN.py
frarch/models/classification/cnn/resnet.py
frarch/models/classification/cnn/vgg.py
frarch/modules/__init__.py
frarch/modules/checkpointer.py
frarch/modules/metrics/__init__.py
frarch/modules/metrics/base.py
frarch/modules/metrics/classification_error.py
frarch/modules/metrics/wrapper.py
frarch/train/__init__.py
frarch/train/base_trainer.py
frarch/train/classifier_trainer.py
frarch/utils/__init__.py
frarch/utils/exceptions.py
frarch/utils/freezable_module_dict.py
frarch/utils/data/__init__.py
frarch/utils/enums/__init__.py
frarch/utils/enums/base.py
frarch/utils/enums/stages.py
frarch/utils/logging/__init__.py
frarch/utils/logging/create_logger.py
frarch-0.1.6.dist-info/LICENSE
frarch-0.1.6.dist-info/METADATA
frarch-0.1.6.dist-info/WHEEL
frarch-0.1.6.dist-info/top_level.txt
frarch-0.1.6.dist-info/RECORD
