Metadata-Version: 2.1
Name: frarch
Version: 0.1.6
Summary: Training Framework for PyTorch projects
Home-page: https://github.com/victorbadenas/frarch
Author: vbadenas
Author-email: victor.badenas@gmail.com
License: MIT
Project-URL: Bug Tracker, https://github.com/victorbadenas/frarch/issues
Project-URL: Changelog, https://github.com/victorbadenas/frarch/blob/master/CHANGELOG.rst
Keywords: deep-learning,framework,pytorch
Platform: any
Classifier: Development Status :: 3 - Alpha
Classifier: Intended Audience :: Developers
Classifier: License :: OSI Approved :: MIT License
Classifier: Natural Language :: English
Classifier: Operating System :: OS Independent
Classifier: Programming Language :: Python :: 3
Classifier: Programming Language :: Python :: 3 :: Only
Classifier: Programming Language :: Python :: 3.8
Classifier: Programming Language :: Python :: 3.9
Classifier: Programming Language :: Python :: 3.10
Classifier: Topic :: Software Development :: Libraries :: Python Modules
Requires-Python: >=3.8
License-File: LICENSE
Requires-Dist: hyperpyyaml (==1.0.1)
Requires-Dist: numpy (==1.23.1)
Requires-Dist: torch (==1.11.0)
Requires-Dist: torchaudio (==0.11.0)
Requires-Dist: torchvision (==0.12.0)
Requires-Dist: tqdm (==4.64.0)
Provides-Extra: dev
Requires-Dist: black (==21.6b0) ; extra == 'dev'
Requires-Dist: frarch[docs] ; extra == 'dev'
Requires-Dist: frarch[test] ; extra == 'dev'
Requires-Dist: identify (>=1.4.20) ; extra == 'dev'
Requires-Dist: pre-commit ; extra == 'dev'
Provides-Extra: docs
Requires-Dist: readthedocs-sphinx-search ; extra == 'docs'
Requires-Dist: sphinx ; extra == 'docs'
Requires-Dist: sphinx-autobuild ; extra == 'docs'
Requires-Dist: sphinx-book-theme ; extra == 'docs'
Requires-Dist: watchdog (<1.0.0) ; extra == 'docs'
Provides-Extra: test
Requires-Dist: coverage ; extra == 'test'
